README.rst
setup.py
pickrr/__init__.py
pickrr/address.py
pickrr/cancelorder.py
pickrr/placeorder.py
pickrr/session.py
pickrr/trackorder.py
pickrr.egg-info/PKG-INFO
pickrr.egg-info/SOURCES.txt
pickrr.egg-info/dependency_links.txt
pickrr.egg-info/not-zip-safe
pickrr.egg-info/requires.txt
pickrr.egg-info/top_level.txt