Metadata-Version: 1.0
Name: pickrr
Version: 0.5
Summary: Pickrr order placing, order Cancellation and order tracking api
Home-page: http://github.com/harishbisht/pickrr
Author: Harish Bisht
Author-email: harish@pickrr.com
License: MIT
Platform: UNKNOWN
